setup.py
sshpt/Generic.py
sshpt/OutputThread.py
sshpt/SSHQueue.py
sshpt/__init__.py
sshpt/__main__.py
sshpt/main.py
sshpt/sshpt.py
sshpt/version.py
sshpt.egg-info/PKG-INFO
sshpt.egg-info/SOURCES.txt
sshpt.egg-info/dependency_links.txt
sshpt.egg-info/entry_points.txt
sshpt.egg-info/requires.txt
sshpt.egg-info/top_level.txt