Metadata-Version: 1.1
Name: sshpt
Version: 1.3.15
Summary: SSH Power Tool, Run commands and copy files to multiple servers simultaneously WITHOUT requiring pre-shared authentication keys
Home-page: https://github.com/haginara/sshpt
Author: Dan McDougall <YouKnowWho@YouKnowWhat.com>,Jonghak Choi <haginara@gmail.com>
Author-email: haginara@gmail.com
License: GNU General Public License (GPL) Version 3
Keywords: ssh administration parallel
Platform: UNKNOWN
Classifier: Development Status :: 4 - Beta
Classifier: License :: OSI Approved :: GNU General Public License (GPL)
Classifier: Operating System :: Unix
Classifier: Environment :: Console
Classifier: Programming Language :: Python :: 2.7
Classifier: Programming Language :: Python :: 3
Classifier: Topic :: System :: Systems Administration
